pctddos/PctRun.py
pct_ddos-1.2.4.dist-info/METADATA
pct_ddos-1.2.4.dist-info/WHEEL
pct_ddos-1.2.4.dist-info/top_level.txt
pct_ddos-1.2.4.dist-info/RECORD
